[
  {
    "id": 1,
    "name": "Barcelona Home Jersey 2025/26",
    "team": "FC Barcelona",
    "category": "Club Jersey",
    "sport": "Football",
    "price": 2490,
    "image": "https://rabonabd.com/wp-content/uploads/2025/09/Untitled-design-29-2.png",
    "rating": 4.7,
    "colors": ["Blue", "Red"],
    "sizes": ["S", "M", "L", "XL", "XXL"],
    "type": "Home",
    "inStock": true,
    "description": "Official home kit replica with breathable fabric and embroidered crest."
  },
  {
    "id": 2,
    "name": "Real Madrid Away Jersey 2025/26",
    "team": "Real Madrid",
    "category": "Club Jersey",
    "sport": "Football",
    "price": 2490,
    "image": "https://rabonabd.com/wp-content/uploads/2025/09/Untitled-design-11-1.png",
    "rating": 4.8,
    "colors": ["Navy"],
    "sizes": ["S", "M", "L", "XL"],
    "type": "Away",
    "inStock": true,
    "description": "Lightweight away kit with moisture-wicking technology."
  },
  {
    "id": 3,
    "name": "Manchester United Home Jersey 2025/26",
    "team": "Manchester United",
    "category": "Club Jersey",
    "sport": "Football",
    "price": 2390,
    "image": "https://diamu.com.bd/wp-content/uploads/2025/06/Manchester-United-Home-Authentic-Jersey-2025-26-Price-in-bd.jpg",
    "rating": 4.5,
    "colors": ["Red"],
    "sizes": ["M", "L", "XL", "XXL"],
    "type": "Home",
    "inStock": true,
    "description": "Classic red home kit with modern fit and ventilated panels."
  },
  {
    "id": 4,
    "name": "Argentina National Team Jersey",
    "team": "Argentina",
    "category": "National Jersey",
    "sport": "Football",
    "price": 2690,
    "image": "https://store.fifa.com/cdn/shop/files/image_ab8f6ea2-c16a-4882-822e-aa52e9506054.png?v=1774372572",
    "rating": 4.9,
    "colors": ["Sky Blue", "White"],
    "sizes": ["S", "M", "L", "XL"],
    "type": "Home",
    "customizable": true,
    "inStock": true,
    "description": "World Cup replica jersey with iconic sky blue stripes."
  },
  {
    "id": 5,
    "name": "Brazil National Team Jersey",
    "team": "Brazil",
    "category": "National Jersey",
    "sport": "Football",
    "price": 2690,
    "image": "https://encrypted-tbn0.gstatic.com/images?q=tbn:ANd9GcT4nstUV9RoNHgVhJOUynO4q3OfOxKBFC6Pz0Zq9htRw-w6_WkwdcfNG1MP&s=10",
    "rating": 4.8,
    "colors": ["Yellow", "Green"],
    "sizes": ["S", "M", "L", "XL", "XXL"],
    "type": "Home",
    "customizable": true,
    "inStock": true,
    "description": "Iconic canary yellow kit worn by five-time world champions."
  },
  {
    "id": 6,
    "name": "Liverpool Home Jersey 2025/26",
    "team": "Liverpool FC",
    "category": "Club Jersey",
    "sport": "Football",
    "price": 2390,
    "image": "https://diamu.com.bd/wp-content/uploads/2025/08/Liverpool-Home-Authentic-Jersey-2025-26-Price-in-Bangladesh.jpg",
    "rating": 4.6,
    "colors": ["Red"],
    "sizes": ["S", "M", "L", "XL"],
    "type": "Home",
    "inStock": true,
    "description": "All-red home kit with classic crest and modern tailored fit."
  },
  {
    "id": 7,
    "name": "PSG Home Jersey 2025/26",
    "team": "Paris Saint-Germain",
    "category": "Club Jersey",
    "sport": "Football",
    "price": 2590,
    "image": "https://rabonabd.com/wp-content/uploads/2025/09/Untitled-design-63-1-300x300.png",
    "rating": 4.6,
    "colors": ["Navy", "Red"],
    "sizes": ["M", "L", "XL", "XXL"],
    "type": "Home",
    "inStock": true,
    "description": "Signature navy and red pinstripe kit with premium finish."
  },
  {
    "id": 8,
    "name": "Portugal National Team Jersey",
    "team": "Portugal",
    "category": "National Jersey",
    "sport": "Football",
    "price": 2690,
    "image": "https://diamu.com.bd/wp-content/uploads/2022/09/Portugal-Home-Authentic-Jersey-World-Cup-Football-2022-4.jpg",
    "rating": 4.7,
    "colors": ["Red", "Green"],
    "sizes": ["S", "M", "L", "XL"],
    "type": "Home",
    "customizable": true,
    "inStock": false,
    "description": "Bold red home kit with green trim, worn by the national squad."
  },
  {
    "id": 9,
    "name": "Bayern Munich Home Jersey 2025/26",
    "team": "Bayern Munich",
    "category": "Club Jersey",
    "sport": "Football",
    "price": 2490,
    "image": "https://img.drz.lazcdn.com/static/bd/p/a3c5903b73a615b44b0e504d9a2668ad.jpg_960x960q80.jpg_.webp",
    "rating": 4.6,
    "colors": ["Red", "White"],
    "sizes": ["S", "M", "L", "XL", "XXL"],
    "type": "Home",
    "inStock": true,
    "description": "Traditional red home kit with white trim and club crest."
  },
  {
    "id": 10,
    "name": "Juventus Home Jersey 2025/26",
    "team": "Juventus",
    "category": "Club Jersey",
    "sport": "Football",
    "price": 2390,
    "image": "https://rabonabd.com/wp-content/uploads/2025/09/Untitled-design-66-1.png",
    "rating": 4.4,
    "colors": ["Black", "White"],
    "sizes": ["M", "L", "XL"],
    "type": "Home",
    "inStock": true,
    "description": "Iconic black and white stripes with a sleek modern cut."
  },
  {
    "id": 11,
    "name": "Retro Brazil 1994 Jersey",
    "team": "Brazil",
    "category": "Retro Jersey",
    "sport": "Football",
    "price": 2990,
    "image": "https://fulltimestore.in/cdn/shop/products/ed96377d-scaled.jpg?v=1687685488",
    "rating": 4.9,
    "colors": ["Yellow"],
    "sizes": ["S", "M", "L", "XL"],
    "type": "Retro",
    "inStock": true,
    "description": "Vintage-inspired replica of the 1994 World Cup winning kit."
  },
  {
    "id": 12,
    "name": "Chicago Bulls Jersey",
    "team": "Chicago Bulls",
    "category": "Club Jersey",
    "sport": "Basketball",
    "price": 2790,
    "image": "https://encrypted-tbn0.gstatic.com/images?q=tbn:ANd9GcQwYd9Nng1a4d0TftByAMNS9NnHDINTTODNlj07ivz6rzLxNN-wMdgGBiW_&s=10",
    "rating": 4.5,
    "colors": ["Red", "Black"],
    "sizes": ["S", "M", "L", "XL", "XXL"],
    "type": "Home",
    "inStock": true,
    "description": "Classic NBA jersey with mesh fabric and embroidered numbers."
  }
]
